bashbuddy/__init__.py
bashbuddy/main.py
bashbuddy/commands/__init__.py
bashbuddy/commands/ask.py
bashbuddy/commands/explain.py
bashbuddy/commands/explain_code.py
bashbuddy/commands/fix.py
bashbuddy/commands/generate.py
bashbuddy/commands/setup.py
bashbuddy/core/__init__.py
bashbuddy/core/llm.py
bashbuddy/core/prompts.py
mybashbuddy-0.2.1.dist-info/METADATA
mybashbuddy-0.2.1.dist-info/WHEEL
mybashbuddy-0.2.1.dist-info/entry_points.txt
mybashbuddy-0.2.1.dist-info/top_level.txt
mybashbuddy-0.2.1.dist-info/RECORD
