Metadata-Version: 2.4
Name: mybashbuddy
Version: 0.2.1
Summary: An AI-powered shell assistant using Google Gemini API
Home-page: https://github.com/Atharvadethe/BashBuddy
Author: Atharva Dethe
Author-email: atharvadethe2004@gmail.com
Project-URL: Bug Reports, https://github.com/Atharvadethe/bashbuddy/issues
Project-URL: Source, https://github.com/Atharvadethe/bashbuddy
Project-URL: Documentation, https://github.com/Atharvadethe/bashbuddy#readme
Keywords: ai,shell,cli,gemini,assistant,automation
Classifier: Development Status :: 3 - Alpha
Classifier: Intended Audience :: Developers
Classifier: License :: OSI Approved :: MIT License
Classifier: Operating System :: OS Independent
Classifier: Programming Language :: Python :: 3
Classifier: Programming Language :: Python :: 3.8
Classifier: Programming Language :: Python :: 3.9
Classifier: Programming Language :: Python :: 3.10
Classifier: Programming Language :: Python :: 3.11
Classifier: Topic :: Software Development :: Libraries :: Python Modules
Classifier: Topic :: System :: Systems Administration
Classifier: Topic :: Utilities
Requires-Python: >=3.8
Requires-Dist: typer
Requires-Dist: rich
Requires-Dist: google-generativeai
Requires-Dist: pyperclip
Dynamic: author
Dynamic: author-email
Dynamic: classifier
Dynamic: description
Dynamic: description-content-type
Dynamic: home-page
Dynamic: keywords
Dynamic: project-url
Dynamic: requires-dist
Dynamic: requires-python
Dynamic: summary
